{"toptracks":{"track":[{"streamable":{"fulltrack":"0","#text":"0"},"mbid":"02b2a039-760c-365b-a4f8-2bacfd8b02c7","name":"Tere Bina","image":[{"size":"small","#text":"https://lastfm.freetls.fastly.net/i/u/34s/2a96cbd8b46e442fc41c2b86b821562f.png"},{"size":"medium","#text":"https://lastfm.freetls.fastly.net/i/u/64s/2a96cbd8b46e442fc41c2b86b821562f.png"},{"size":"large","#text":"https://lastfm.freetls.fastly.net/i/u/174s/2a96cbd8b46e442fc41c2b86b821562f.png"},{"size":"extralarge","#text":"https://lastfm.freetls.fastly.net/i/u/300x300/2a96cbd8b46e442fc41c2b86b821562f.png"}],"artist":{"url":"https://www.last.fm/music/A.R.+Rahman","name":"A.R. Rahman","mbid":""},"url":"https://www.last.fm/music/A.R.+Rahman/_/Tere+Bina","duration":"307","@attr":{"rank":"1"},"playcount":"9"},{"streamable":{"fulltrack":"0","#text":"0"},"mbid":"","name":"Ma Belle","image":[{"size":"small","#text":"https://lastfm.freetls.fastly.net/i/u/34s/2a96cbd8b46e442fc41c2b86b821562f.png"},{"size":"medium","#text":"https://lastfm.freetls.fastly.net/i/u/64s/2a96cbd8b46e442fc41c2b86b821562f.png"},{"size":"large","#text":"https://lastfm.freetls.fastly.net/i/u/174s/2a96cbd8b46e442fc41c2b86b821562f.png"},{"size":"extralarge","#text":"https://lastfm.freetls.fastly.net/i/u/300x300/2a96cbd8b46e442fc41c2b86b821562f.png"}],"artist":{"url":"https://www.last.fm/music/AP+Dhillon","name":"AP Dhillon","mbid":""},"url":"https://www.last.fm/music/AP+Dhillon/_/Ma+Belle","duration":"160","@attr":{"rank":"2"},"playcount":"8"},{"streamable":{"fulltrack":"0","#text":"0"},"mbid":"","name":"Afreen Afreen","image":[{"size":"small","#text":"https://lastfm.freetls.fastly.net/i/u/34s/2a96cbd8b46e442fc41c2b86b821562f.png"},{"size":"medium","#text":"https://lastfm.freetls.fastly.net/i/u/64s/2a96cbd8b46e442fc41c2b86b821562f.png"},{"size":"large","#text":"https://lastfm.freetls.fastly.net/i/u/174s/2a96cbd8b46e442fc41c2b86b821562f.png"},{"size":"extralarge","#text":"https://lastfm.freetls.fastly.net/i/u/300x300/2a96cbd8b46e442fc41c2b86b821562f.png"}],"artist":{"url":"https://www.last.fm/music/Rahat+Fateh+Ali+Khan","name":"Rahat Fateh Ali Khan","mbid":""},"url":"https://www.last.fm/music/Rahat+Fateh+Ali+Khan/_/Afreen+Afreen","duration":"0","@attr":{"rank":"3"},"playcount":"8"},{"streamable":{"fulltrack":"0","#text":"0"},"mbid":"","name":"Excuses","image":[{"size":"small","#text":"https://lastfm.freetls.fastly.net/i/u/34s/2a96cbd8b46e442fc41c2b86b821562f.png"},{"size":"medium","#text":"https://lastfm.freetls.fastly.net/i/u/64s/2a96cbd8b46e442fc41c2b86b821562f.png"},{"size":"large","#text":"https://lastfm.freetls.fastly.net/i/u/174s/2a96cbd8b46e442fc41c2b86b821562f.png"},{"size":"extralarge","#text":"https://lastfm.freetls.fastly.net/i/u/300x300/2a96cbd8b46e442fc41c2b86b821562f.png"}],"artist":{"url":"https://www.last.fm/music/AP+Dhillon","name":"AP Dhillon","mbid":""},"url":"https://www.last.fm/music/AP+Dhillon/_/Excuses","duration":"176","@attr":{"rank":"4"},"playcount":"6"},{"streamable":{"fulltrack":"0","#text":"0"},"mbid":"","name":"Insane","image":[{"size":"small","#text":"https://lastfm.freetls.fastly.net/i/u/34s/2a96cbd8b46e442fc41c2b86b821562f.png"},{"size":"medium","#text":"https://lastfm.freetls.fastly.net/i/u/64s/2a96cbd8b46e442fc41c2b86b821562f.png"},{"size":"large","#text":"https://lastfm.freetls.fastly.net/i/u/174s/2a96cbd8b46e442fc41c2b86b821562f.png"},{"size":"extralarge","#text":"https://lastfm.freetls.fastly.net/i/u/300x300/2a96cbd8b46e442fc41c2b86b821562f.png"}],"artist":{"url":"https://www.last.fm/music/AP+Dhillon","name":"AP Dhillon","mbid":""},"url":"https://www.last.fm/music/AP+Dhillon/_/Insane","duration":"207","@attr":{"rank":"5"},"playcount":"6"}],"@attr":{"user":"KrishSkywalker","totalPages":"33","page":"1","total":"164","perPage":"5"}}}